<annotation>
	<folder>chinook_jpg</folder>
	<filename>105.jpg</filename>
	<path>F:\chinook_jpg\105.jpg</path>
	<source>
		<database>Unknown</database>
	</source>
	<size>
		<width>960</width>
		<height>410</height>
		<depth>3</depth>
	</size>
	<segmented>0</segmented>
	<object>
		<name>chinook</name>
		<pose>Unspecified</pose>
		<truncated>0</truncated>
		<difficult>0</difficult>
		<bndbox>
			<xmin>112</xmin>
			<ymin>32</ymin>
			<xmax>858</xmax>
			<ymax>404</ymax>
		</bndbox>
	</object>
</annotation>
